pycovid19lstm/covid19lstm.py
pycovid19lstm/lstm2countery.py
pycovid19lstm-0.2.0.dist-info/LICENSE
pycovid19lstm-0.2.0.dist-info/METADATA
pycovid19lstm-0.2.0.dist-info/WHEEL
pycovid19lstm-0.2.0.dist-info/top_level.txt
pycovid19lstm-0.2.0.dist-info/RECORD
